{
    "content": [
        {
            "id": "action_start",
            "selector": "setHighlighted:",
            "values": [
                true,
                "BCB",
                "SCON"
            ]
        },
        {
            "id": "action_addflag_EtCO2",
            "selector": "setFlag:",
            "values": [
                true,
                "EtCO2"
            ]
        },
        {
            "id": "action_rmflag_CCC",
            "selector": "setFlag:",
            "values": [
                false,
                "CCC"
            ]
        },
        {
            "id": "action_unhighlight",
            "selector": "setHighlighted:",
            "values": [
                false,
                "*"
            ]
        },
        {
            "id": "action_stopRepeat",
            "selector": "stopRepeat:",
            "values": [
                "*"
            ]
        },
        {
            "id": "action_popCountdownIndicator",
            "selector": "popCountdownIndicator:",
            "values": [
                "*"
            ]
        },
        {
            "id": "action_terminate",
            "selector": "terminate",
            "flag": {}
        },
        {
            "id": "action_ROSC",
            "selector": "ROSC",
            "flag": {}
        },
        {
            "id": "action_highlight_ACH",
            "selector": "setHighlighted:",
            "values": [
                true,
                "ACH"
            ]
        },
        {
            "id": "action_highlight_CCP",
            "selector": "setHighlighted:",
            "values": [
                true,
                "CCP"
            ]
        },
        {
            "id": "action_highlight_AOP",
            "selector": "setHighlighted:",
            "flag": {
                "value": false,
                "key": "AOP"
            },
            "values": [
                true,
                "AOP"
            ]
        },
        {
            "id": "action_addflag_AOP",
            "selector": "setFlag:",
            "values": [
                "ture",
                "AOP"
            ]
        },
        {
            "id": "action_highlight_CCC",
            "selector": "setHighlighted:",
            "flag": {
                "value": false,
                "key": "CCC"
            },
            "values": [
                true,
                "CCC"
            ]
        },
        {
            "id": "action_highlight_DMO",
            "selector": "setHighlighted:",
            "flag": {
                "value": false,
                "key": "DMO"
            },
            "values": [
                true,
                "DMO"
            ]
        },
        {
            "id": "action_highlight_ADA_flag",
            "selector": "setHighlighted:",
            "flag": {
                "value": false,
                "key": "ADA"
            },
            "values": [
                true,
                "ADA"
            ]
        },
        {
            "id": "action_highlight_NLI",
            "selector": "setHighlighted:",
            "flag": {
                "value": false,
                "key": "NLI"
            },
            "values": [
                "ture",
                "NLI"
            ]
        },
        {
            "id": "action_addflag_NLI",
            "selector": "setFlag:",
            "values": [
                "ture",
                "NLI"
            ]
        },
        {
            "id": "action_highlight_NVS",
            "selector": "setHighlighted:",
            "values": [
                true,
                "NVS"
            ]
        },
        {
            "id": "action_playSound_CPR",
            "selector": "playSound:",
            "repeat": -1,
            "interval": 0.5,
            "values": [
                "CPR"
            ]
        },
        {
            "id": "action_playSound_CPR_30",
            "selector": "playSound:",
            "repeat": 30,
            "interval": 0.5,
            "values": [
                "CPR"
            ]
        },
        {
            "id": "action_playSound_respiration_repeat",
            "selector": "playSound:",
            "flag": {
                "value": true,
                "key": "ADA"
            },
            "repeat": -1,
            "interval": 6,
            "values": [
                "respiration"
            ]
        },
        {
            "id": "action_popCountdownIndicator_CCP",
            "selector": "popCountdownIndicator:",
            "values": [
                "CCP"
            ]
        },
        {
            "id": "action_pushCountdownIndicator_CCP",
            "selector": "pushCountdownIndicator:",
            "values": [
                120,
                "CCP"
            ]
        },
        {
            "id": "action_highlight_CCP_repeat",
            "selector": "setHighlighted:",
            "values": [
                true,
                "CCP"
            ]
        },
        {
            "id": "action_popCountdownIndicator_DCR",
            "selector": "popCountdownIndicator:",
            "flag": {
                "value": true,
                "key": "DMO"
            },
            "values": [
                "DCR"
            ]
        },
        {
            "id": "action_pushCountdownIndicator_DCR",
            "selector": "pushCountdownIndicator:",
            "flag": {
                "value": true,
                "key": "DMO"
            },
            "values": [
                120,
                "DCR"
            ]
        },
        {
            "id": "action_highlight_DCR_repeat",
            "selector": "setHighlighted:",
            "flag": {
                "value": true,
                "key": "DMO"
            },
            "values": [
                true,
                "DCR"
            ]
        },
        {
            "id": "action_popCountdownIndicator_SCPRET",
            "selector": "popCountdownIndicator:",
            "flag": {
                "value": true,
                "key": "EtCO2"
            },
            "values": [
                "SCPRET"
            ]
        },
        {
            "id": "action_pushCountdownIndicator_SCPRET",
            "selector": "pushCountdownIndicator:",
            "flag": {
                "value": true,
                "key": "EtCO2"
            },
            "values": [
                120,
                "SCPRET"
            ]
        },
        {
            "id": "action_highlight_SCPRET_repeat",
            "selector": "setHighlighted:",
            "flag": {
                "value": true,
                "key": "EtCO2"
            },
            "values": [
                true,
                "SCPRET"
            ]
        },
        {
            "id": "action_highlight_PAD",
            "selector": "setHighlighted:",
            "flag": {
                "value": false,
                "key": "CCC"
            },
            "values": [
                true,
                "PAD"
            ]
        },
        {
            "id": "action_addflag_CCC",
            "selector": "setFlag:",
            "values": [
                true,
                "CCC"
            ]
        },
        {
            "id": "action_stopRepeat_setPAD",
            "selector": "stopRepeat:",
            "flag": {
                "value": true,
                "key": "setPAD"
            },
            "values": [
                "set_PAD"
            ]
        },
        {
            "id": "action_rmflag_setPAD",
            "selector": "setFlag:",
            "values": [
                false,
                "setPAD"
            ]
        },
        {
            "id": "action_addflag_setPAD",
            "selector": "setFlag:",
            "values": [
                true,
                "setPAD"
            ]
        },
        {
            "id": "action_pushCountdownIndicator_PAD",
            "selector": "pushCountdownIndicator:",
            "values": [
                240,
                "PAD"
            ]
        },
        {
            "id": "action_popCountdownIndicator_PAD",
            "selector": "popCountdownIndicator:",
            "delay": 240,
            "values": [
                "PAD"
            ]
        },
        {
            "id": "action_highlight_PAD_noflag",
            "selector": "setHighlighted:",
            "values": [
                true,
                "PAD"
            ]
        },
        {
            "id": "action_stopRepeat_playCPR",
            "selector": "stopRepeat:",
            "values": [
                "action_playSound_CPR",
                "action_playSound_CPR_30"
            ]
        },
        {
            "id": "action_playSound_respiration",
            "selector": "playSound:",
            "values": [
                "respiration"
            ]
        },
        {
            "id": "action_addflag_ACO",
            "selector": "setFlag:",
            "flag": {
                "value": true,
                "key": "ADA"
            },
            "values": [
                true,
                "ACO"
            ]
        },
        {
            "id": "action_addflag_ADA",
            "selector": "setFlag:",
            "flag": {
                "value": false,
                "key": "ADA"
            },
            "values": [
                true,
                "ADA"
            ]
        },
        {
            "id": "action_unhighlight_setACOY",
            "selector": "setHighlighted:",
            "flag": {
                "value": true,
                "key": "ACO"
            },
            "values": [
                false,
                "ACOSC",
                "ACOBS",
                "ACOET",
                "ACOTR"
            ]
        },
        {
            "id": "action_highlight_ADA",
            "selector": "setHighlighted:",
            "values": [
                true,
                "ADA"
            ]
        },
        {
            "id": "action_unhighlight_setACON",
            "selector": "setHighlighted:",
            "values": [
                false,
                "ACOSC",
                "ACOBS",
                "ACOET",
                "ACOTR"
            ]
        },
        {
            "id": "action_rmflag_ADA",
            "selector": "setFlag:",
            "values": [
                false,
                "ADA"
            ]
        },
        {
            "id": "action_highlight_setADA",
            "selector": "setHighlighted:",
            "values": [
                true,
                "ACOSC",
                "ACOBS",
                "ACOET",
                "ACOTR"
            ]
        },
        {
            "id": "action_rmflag_setADA",
            "selector": "setFlag:",
            "values": [
                false,
                "ACO",
                "ADA"
            ]
        },
        {
            "id": "action_addflag_DDE3",
            "selector": "setFlag:",
            "flag": {
                "value": true,
                "key": "DDE2"
            },
            "values": [
                true,
                "DDE3"
            ]
        },
        {
            "id": "action_addflag_DDE2",
            "selector": "setFlag:",
            "flag": {
                "value": true,
                "key": "DDE"
            },
            "values": [
                true,
                "DDE2"
            ]
        },
        {
            "id": "action_addflag_DDE",
            "selector": "setFlag:",
            "flag": {
                "value": false,
                "key": "DDE3"
            },
            "values": [
                true,
                "DDE"
            ]
        },
        {
            "id": "action_rmflag_setDDE",
            "selector": "setFlag:",
            "flag": {
                "value": true,
                "key": "DDE3"
            },
            "values": [
                false,
                "DDE2",
                "DDE"
            ]
        },
        {
            "id": "action_highlight_DCR",
            "selector": "setHighlighted:",
            "flag": {
                "value": false,
                "key": "DMO"
            },
            "values": [
                true,
                "DCR"
            ]
        },
        {
            "id": "action_addflag_DMO",
            "selector": "setFlag:",
            "values": [
                true,
                "DMO"
            ]
        },
        {
            "id": "action_highlight_DDE",
            "selector": "setHighlighted:",
            "values": [
                true,
                "DDE"
            ]
        },
        {
            "id": "action_highlight_PAM",
            "selector": "setHighlighted:",
            "flag": {
                "value": true,
                "key": "DDE2"
            },
            "values": [
                true,
                "PAM"
            ]
        },
        {
            "id": "action_addCount_PAD",
            "selector": "addCount:",
            "values": [
                1,
                "PAD"
            ]
        },
        {
            "id": "action_addCount_PBI",
            "selector": "addCount:",
            "values": [
                1,
                "PBI"
            ]
        },
        {
            "id": "action_addCount_PCA",
            "selector": "addCount:",
            "values": [
                1,
                "PCA"
            ]
        },
        {
            "id": "action_addCount_PAT",
            "selector": "addCount:",
            "values": [
                1,
                "PAT"
            ]
        },
        {
            "id": "action_addCount_PAM",
            "selector": "addCount:",
            "values": [
                1,
                "PAM"
            ]
        },
        {
            "id": "action_addCount_PMG",
            "selector": "addCount:",
            "values": [
                1,
                "PMG"
            ]
        },
        {
            "id": "action_addCount_PLI",
            "selector": "addCount:",
            "values": [
                1,
                "PLI"
            ]
        },
        {
            "id": "action_addCount_PGL",
            "selector": "addCount:",
            "values": [
                1,
                "PGL"
            ]
        },
        {
            "id": "action_addCount_PRE",
            "selector": "addCount:",
            "values": [
                1,
                "PRE"
            ]
        },
        {
            "id": "action_addCount_PD4",
            "selector": "addCount:",
            "values": [
                1,
                "PD4"
            ]
        },
        {
            "id": "action_addCount_PD8",
            "selector": "addCount:",
            "values": [
                1,
                "PD8"
            ]
        },
        {
            "id": "action_addCount_PN8",
            "selector": "addCount:",
            "values": [
                1,
                "PN8"
            ]
        },
        {
            "id": "action_addCount_PNO",
            "selector": "addCount:",
            "values": [
                1,
                "PNO"
            ]
        },
        {
            "id": "action_addCount_PATR",
            "selector": "addCount:",
            "values": [
                1,
                "PATR"
            ]
        },
        {
            "id": "action_addCount_PKE",
            "selector": "addCount:",
            "values": [
                1,
                "PKE"
            ]
        },
        {
            "id": "action_addCount_PSU",
            "selector": "addCount:",
            "values": [
                1,
                "PSU"
            ]
        },
        {
            "id": "action_addCount_PMI",
            "selector": "addCount:",
            "values": [
                1,
                "PMI"
            ]
        }
    ],
    "version": "0.0.1"
}
